datapie/__init__.py
datapie/descriptions.py
datapie/has_invariant.py
datapie/has_variants.py
datapie/iterators.py
datapie/main.py
datapie/pyrightconfig.json
datapie/views.py
datapie/wrongdoings.py
datapie/chartpacks/main.py
datapie/databoxes/__init__.py
datapie/databoxes/_exports.py
datapie/databoxes/_imports.py
datapie/databoxes/_imports2.py
datapie/databoxes/_imports3.py
datapie/databoxes/_jsonables.py
datapie/databoxes/_merge.py
datapie/databoxes/_views.py
datapie/databoxes/main.py
datapie/dates/__init__.py
datapie/dates/frequencies.py
datapie/dates/periods.py
datapie/ez_plotly/__init__.py
datapie/ez_plotly/chartboxes.py
datapie/ez_plotly/main.py
datapie/series/__init__.py
datapie/series/_broadcasts.py
datapie/series/_categories.py
datapie/series/_conversions.py
datapie/series/_elementwise.py
datapie/series/_ell_one.py
datapie/series/_extrapolate.py
datapie/series/_filling.py
datapie/series/_functionalize.py
datapie/series/_hp.py
datapie/series/_indexing.py
datapie/series/_jsonables.py
datapie/series/_lays.py
datapie/series/_moving.py
datapie/series/_plotly.py
datapie/series/_statistics.py
datapie/series/_temporal.py
datapie/series/_timing.py
datapie/series/_views.py
datapie/series/_x13.py
datapie/series/arip.py
datapie/series/functions.py
datapie/series/main.py
datapie/series/plotly_styles/plain_layout.json
datapie/x13_runners_1_1_39/__init__.py
datapie/x13_runners_1_1_39/darwin/__init__.py
datapie/x13_runners_1_1_39/darwin/libgcc_s.1.dylib
datapie/x13_runners_1_1_39/darwin/libgfortran.3.dylib
datapie/x13_runners_1_1_39/darwin/libquadmath.0.dylib
datapie/x13_runners_1_1_39/darwin/main.py
datapie/x13_runners_1_1_39/darwin/x13as_ascii
datapie/x13_runners_1_1_39/linux/__init__.py
datapie/x13_runners_1_1_39/linux/main.py
datapie/x13_runners_1_1_39/linux/x13as_ascii
datapie/x13_runners_1_1_39/windows/__init__.py
datapie/x13_runners_1_1_39/windows/main.py
datapie/x13_runners_1_1_39/windows/x12as_ascii.exe
datapie/x13_runners_1_1_62/__init__.py
datapie-0.4.0.dist-info/METADATA
datapie-0.4.0.dist-info/WHEEL
datapie-0.4.0.dist-info/licenses/LICENSE
datapie-0.4.0.dist-info/RECORD
