Metadata-Version: 2.4
Name: datapie
Version: 0.4.0
Summary: Time series and data management for macroeconomic modeling
Project-URL: Homepage, https://github.com/iris-solutions-team/datapie
Project-URL: Documentation, https://iris-solutions-team.github.io/datapie-pages
Project-URL: Bug Tracker, https://github.com/iris-solutions-team/datapie/issues
Author-email: Jaromir Benes <jaromir.benes@gmail.com>
License: MIT
License-File: LICENSE
Keywords: charts,data,dates,time series
Classifier: License :: OSI Approved :: MIT License
Classifier: Operating System :: OS Independent
Classifier: Programming Language :: Python :: 3
Requires-Python: >=3.11
Requires-Dist: daqp>=0.6.0
Requires-Dist: documark>=0.4.0
Requires-Dist: numpy>=2.1
Requires-Dist: plotly>=6.3
Requires-Dist: scipy>=1.14.1
